leina/__init__.py
leina/__main__.py
leina/py.typed
leina-0.0.0.dist-info/entry_points.txt
leina-0.0.0.dist-info/LICENSE
leina-0.0.0.dist-info/WHEEL
leina-0.0.0.dist-info/METADATA
leina-0.0.0.dist-info/RECORD
