Metadata-Version: 2.1
Name: leina
Version: 0.0.0
Summary: Saffire
Home-page: https://github.com/csala/leina
License: MIT
Author: Carles Sala
Author-email: carles@pythiac.com
Requires-Python: >=3.8,<4.0
Classifier: Development Status :: 1 - Planning
Classifier: License :: OSI Approved :: MIT License
Classifier: Programming Language :: Python :: 3
Classifier: Programming Language :: Python :: 3.10
Classifier: Programming Language :: Python :: 3.8
Classifier: Programming Language :: Python :: 3.9
Project-URL: Changelog, https://github.com/csala/leina/releases
Project-URL: Documentation, https://leina.readthedocs.io
Project-URL: Repository, https://github.com/csala/leina
